fds/__init__.py
fds/sdk/__init__.py
fds/sdk/FactSetEstimates/__init__.py
fds/sdk/FactSetEstimates/api_client.py
fds/sdk/FactSetEstimates/configuration.py
fds/sdk/FactSetEstimates/exceptions.py
fds/sdk/FactSetEstimates/model_utils.py
fds/sdk/FactSetEstimates/rest.py
fds/sdk/FactSetEstimates/api/__init__.py
fds/sdk/FactSetEstimates/api/actuals_api.py
fds/sdk/FactSetEstimates/api/broker_detail_api.py
fds/sdk/FactSetEstimates/api/consensus_api.py
fds/sdk/FactSetEstimates/api/data_items_api.py
fds/sdk/FactSetEstimates/api/estimates_and_ratings_reports_api.py
fds/sdk/FactSetEstimates/api/guidance_api.py
fds/sdk/FactSetEstimates/api/ratings_api.py
fds/sdk/FactSetEstimates/api/segment_actuals_api.py
fds/sdk/FactSetEstimates/api/segments_api.py
fds/sdk/FactSetEstimates/api/surprise_api.py
fds/sdk/FactSetEstimates/apis/__init__.py
fds/sdk/FactSetEstimates/model/__init__.py
fds/sdk/FactSetEstimates/model/actual.py
fds/sdk/FactSetEstimates/model/actuals_request.py
fds/sdk/FactSetEstimates/model/actuals_response.py
fds/sdk/FactSetEstimates/model/analyst_rating.py
fds/sdk/FactSetEstimates/model/analyst_rating_response.py
fds/sdk/FactSetEstimates/model/category.py
fds/sdk/FactSetEstimates/model/company_reports_error_response.py
fds/sdk/FactSetEstimates/model/consensus_estimate.py
fds/sdk/FactSetEstimates/model/consensus_ratings.py
fds/sdk/FactSetEstimates/model/consensus_ratings_request.py
fds/sdk/FactSetEstimates/model/consensus_ratings_response.py
fds/sdk/FactSetEstimates/model/consensus_response.py
fds/sdk/FactSetEstimates/model/detail_estimate.py
fds/sdk/FactSetEstimates/model/detail_ratings.py
fds/sdk/FactSetEstimates/model/detail_ratings_request.py
fds/sdk/FactSetEstimates/model/detail_ratings_response.py
fds/sdk/FactSetEstimates/model/detail_response.py
fds/sdk/FactSetEstimates/model/error_object.py
fds/sdk/FactSetEstimates/model/error_response.py
fds/sdk/FactSetEstimates/model/error_response_sub_errors.py
fds/sdk/FactSetEstimates/model/estimate.py
fds_sdk_factsetestimates-2.1.0.dist-info/licenses/LICENSE
fds_sdk_factsetestimates-2.1.0.dist-info/METADATA
fds_sdk_factsetestimates-2.1.0.dist-info/WHEEL
fds_sdk_factsetestimates-2.1.0.dist-info/top_level.txt
fds_sdk_factsetestimates-2.1.0.dist-info/RECORD
